git_contrib_tree/git-contrib-tree
git_contrib_tree/wrapper.py
git_contrib_tree-0.1.1.dist-info/METADATA
git_contrib_tree-0.1.1.dist-info/WHEEL
git_contrib_tree-0.1.1.dist-info/entry_points.txt
git_contrib_tree-0.1.1.dist-info/licenses/LICENSE
git_contrib_tree-0.1.1.dist-info/RECORD
