Metadata-Version: 2.4
Name: git-contrib-tree
Version: 0.1.1
Summary: Analyze and visualize git repository contributions with a file tree showing top contributors.
Project-URL: Repository, https://gitlab.com/wykwit/git-contrib-tree
Project-URL: Issues, https://gitlab.com/wykwit/git-contrib-tree/issues
Author-email: "Wiktor W." <wykwit@disroot.org>
License-File: LICENSE
Keywords: analysis,cli,contributions,git,tree,visualization
Classifier: Development Status :: 4 - Beta
Classifier: Environment :: Console
Classifier: Intended Audience :: Developers
Classifier: License :: OSI Approved :: MIT License
Classifier: Operating System :: OS Independent
Classifier: Programming Language :: Python :: 3
Classifier: Programming Language :: Python :: 3.6
Classifier: Programming Language :: Python :: 3.7
Classifier: Programming Language :: Python :: 3.8
Classifier: Programming Language :: Python :: 3.9
Classifier: Programming Language :: Python :: 3.10
Classifier: Programming Language :: Python :: 3.11
Classifier: Programming Language :: Python :: 3.12
Classifier: Topic :: Software Development :: Version Control :: Git
Classifier: Topic :: Utilities
Requires-Python: >=3.6
